nonebot_plugin_suggaradapter_cf-0.1.dist-info/METADATA
nonebot_plugin_suggaradapter_cf-0.1.dist-info/WHEEL
nonebot_plugin_suggaradapter_cf-0.1.dist-info/entry_points.txt
nonebot_plugin_suggaradapter_cf-0.1.dist-info/licenses/LICENSE
nonebot_plugin_suggaradapter_cf/__init__.py
nonebot_plugin_suggaradapter_cf/core.py
nonebot_plugin_suggaradapter_cf-0.1.dist-info/RECORD
