Metadata-Version: 2.1
Name: nonebot_plugin_suggaradapter_cf
Version: 0.1
Summary: CloudFlare procotol adapter for SuggaarChat
Keywords: chat", "suggar", "nonebot
Author-Email: JohnRichard4096 <windowserror@163.com>
License: GPL-3.0-or-later
Project-URL: Homepage, https://github.com/JohnRichard4096/nonebot_plugin_suggaradapter_cf
Project-URL: Source, https://github.com/JohnRichard4096/nonebot_plugin_suggaradapter_cf
Project-URL: Issue Tracker, https://github.com/JohnRichard4096/nonebot_plugin_suggaradapter_cf/issues
Requires-Python: <4.0,>=3.9
Requires-Dist: nonebot2>=2.2.0
Requires-Dist: nonebot-plugin-suggarchat>=1.15.0
Requires-Dist: nonebot-adapter-onebot>=2.0.0
Requires-Dist: aiohttp>=3.9.0
